pyStatsCan/__init__.py
pyStatsCan-0.0.1.post1.dist-info/LICENSE
pyStatsCan-0.0.1.post1.dist-info/METADATA
pyStatsCan-0.0.1.post1.dist-info/WHEEL
pyStatsCan-0.0.1.post1.dist-info/top_level.txt
pyStatsCan-0.0.1.post1.dist-info/RECORD
