Metadata-Version: 2.1
Name: pyStatsCan
Version: 0.0.1.post1
Summary: A python wrapper for Statistics Canada Web Data Services API
Home-page: https://github.com/DelBiss/pyStatsCan
Author: Philippe Allard-Rousse
Author-email: philrousse@gmail.com
License: Apache 2.0
Platform: UNKNOWN
Classifier: Development Status :: 1 - Planning
Classifier: Programming Language :: Python :: 3
Classifier: License :: OSI Approved :: Apache Software License
Classifier: Operating System :: OS Independent
